WSS_ToolKit/__init__.py
WSS_ToolKit/WConfigUtils/ConfigUtils.py
WSS_ToolKit/WConfigUtils/__init__.py
WSS_ToolKit/WGeometryUtils/GeometryUtils.py
WSS_ToolKit/WGeometryUtils/__init__.py
WSS_ToolKit-0.0.4.dist-info/LICENCE
WSS_ToolKit-0.0.4.dist-info/METADATA
WSS_ToolKit-0.0.4.dist-info/WHEEL
WSS_ToolKit-0.0.4.dist-info/top_level.txt
WSS_ToolKit-0.0.4.dist-info/RECORD
